sm_ms_api/__init__.py
sm_ms_api-0.3.4.dist-info/LICENSE
sm_ms_api-0.3.4.dist-info/METADATA
sm_ms_api-0.3.4.dist-info/WHEEL
sm_ms_api-0.3.4.dist-info/RECORD
