Metadata-Version: 2.1
Name: sm-ms-api
Version: 0.3.4
Summary: 
License: MIT
Author: kaesinol
Author-email: keiplyer@gmail.com
Requires-Python: >=3.11,<4.0
Classifier: License :: OSI Approved :: MIT License
Classifier: Programming Language :: Python :: 3
Classifier: Programming Language :: Python :: 3.11
Requires-Dist: requests (>=2.31.0,<3.0.0)
